bethany/__init__.py
bethany/bethany.py
bethany-1.0.8.dist-info/LICENSE
bethany-1.0.8.dist-info/METADATA
bethany-1.0.8.dist-info/WHEEL
bethany-1.0.8.dist-info/entry_points.txt
bethany-1.0.8.dist-info/top_level.txt
bethany-1.0.8.dist-info/RECORD
