Metadata-Version: 2.1
Name: bethany
Version: 1.0.8
Summary: A command line tool to list all BUG, TODO, HACK, NOTE, and FIXME keywords in your code.
Home-page: https://github.com/raultapia
Author: Raul Tapia
Author-email: raultapia@us.es
License: GPLv3
Platform: UNKNOWN
License-File: LICENSE
Requires-Dist: argparse
